ftl_agent/Gradio_UI.py
ftl_agent/__init__.py
ftl_agent/agents.py
ftl_agent/cli.py
ftl_agent/codegen.py
ftl_agent/core.py
ftl_agent/default_tools.py
ftl_agent/local_python_executor.py
ftl_agent/memory.py
ftl_agent/prompts.py
ftl_agent/shell.py
ftl_agent/tools.py
ftl_agent/ui.py
ftl_agent/util.py
ftl_agent/prompts/__init__.py
ftl_agent/prompts/code_agent.yaml
ftl_agent/prompts/ftl_agent.yaml
ftl_agent-0.1.2.dist-info/LICENSE
ftl_agent-0.1.2.dist-info/METADATA
ftl_agent-0.1.2.dist-info/WHEEL
ftl_agent-0.1.2.dist-info/entry_points.txt
ftl_agent-0.1.2.dist-info/top_level.txt
ftl_agent-0.1.2.dist-info/RECORD
